OCR_with_format/__init__.py
OCR_with_format/__main__.py
OCR_with_format/ocr_with_format.py
ocr_with_format-0.14.dist-info/licenses/LICENSE
ocr_with_format-0.14.dist-info/METADATA
ocr_with_format-0.14.dist-info/WHEEL
ocr_with_format-0.14.dist-info/entry_points.txt
ocr_with_format-0.14.dist-info/top_level.txt
ocr_with_format-0.14.dist-info/RECORD
