Metadata-Version: 2.4
Name: OCR_with_format
Version: 0.14
Summary: Wrapper to pytesseract to preserve space and formatting
Author: thiswillbeyourgithub
Project-URL: Homepage, https://github.com/thiswillbeyourgithub/OCR_with_format
Keywords: OCR,tesseract,pytesseract,format,formatting,space,spacing,spaces
Classifier: Programming Language :: Python
Classifier: Programming Language :: Python :: 3
Requires-Python: >=3.9
License-File: LICENSE
Requires-Dist: beautifulsoup4>=4.10.0
Requires-Dist: fire>=0.5.0
Requires-Dist: ftfy>=6.1.1
Requires-Dist: numpy>=1.21.5
Requires-Dist: opencv-python>=4.7.0.72
Requires-Dist: pytesseract>=0.3.10
Requires-Dist: beartype>=0.19.0
Requires-Dist: pandas>=2.2.3
Dynamic: author
Dynamic: classifier
Dynamic: description
Dynamic: description-content-type
Dynamic: keywords
Dynamic: license-file
Dynamic: project-url
Dynamic: requires-dist
Dynamic: requires-python
Dynamic: summary
